{
    "title": "Configuring Azurite to emulate Azure Storage",
	"description": "",
	"icon": "fa-csharp",
	"difficulty": "beginner",
    "time": "10 minutes",
	"details": {
		"steps": [
			{
				"title": "Exercise: Empty",
				"text": "01-empty/content.md"
			}
		],
		"intro": {
			"text": "00-introduction/content.md",
			"courseData": "00-introduction/background.sh"
		},
		"finish": {
			"text": "07-conclusion/content.md"
		}
	},
	"files": [
		"Application.csproj",
		"Program.cs"
	],
	"environment": {
		"showdashboard": true,
		"uilayout": "editor-terminal",
		"uisettings": "csharp",		
		"terminals": [
			{
				"name": "Running Azurite", 
				"command": "docker run -p 10000:10000 mcr.microsoft.com/azure-storage/azurite", 
				"target": "host01"
			}
		]
	},
	"backend": {
		"imageid": "dotnet"
	}
}